deeppath/__init__.py
deeppath/_version.py
deeppath/deeppath.py
deeppath/py.typed
deeppath-1.0.0.dist-info/AUTHORS.rst
deeppath-1.0.0.dist-info/LICENSE
deeppath-1.0.0.dist-info/METADATA
deeppath-1.0.0.dist-info/WHEEL
deeppath-1.0.0.dist-info/top_level.txt
deeppath-1.0.0.dist-info/RECORD
