Metadata-Version: 2.1
Name: deeppath
Version: 1.0.0
Summary: Python module to easily manipulate complex nested structures
License: MIT license
Keywords: deeppath
Classifier: Development Status :: 2 - Pre-Alpha
Classifier: Intended Audience :: Developers
Classifier: License :: OSI Approved :: MIT License
Classifier: Natural Language :: English
Classifier: Programming Language :: Python :: 3
Classifier: Programming Language :: Python :: 3.6
Classifier: Programming Language :: Python :: 3.7
Classifier: Programming Language :: Python :: 3.8
Classifier: Programming Language :: Python :: 3.9
Classifier: Programming Language :: Python :: 3.10
Classifier: Programming Language :: Python :: 3.11
Requires-Python: >=3.6
License-File: LICENSE
License-File: AUTHORS.rst
Provides-Extra: dev
Requires-Dist: pytest ; extra == 'dev'
Requires-Dist: mypy ; extra == 'dev'
Requires-Dist: esbonio ; extra == 'dev'
Requires-Dist: pylint ; extra == 'dev'
Requires-Dist: doc8 ; extra == 'dev'
Requires-Dist: black ; extra == 'dev'
Requires-Dist: towncrier ; extra == 'dev'
Requires-Dist: ruff ; extra == 'dev'
Requires-Dist: dataclasses ; (python_version < "3.7") and extra == 'dev'
